README.rst
setup.py
jobcan/__init__.py
jobcan/jobcan.py
jobcan.egg-info/PKG-INFO
jobcan.egg-info/SOURCES.txt
jobcan.egg-info/dependency_links.txt
jobcan.egg-info/entry_points.txt
jobcan.egg-info/requires.txt
jobcan.egg-info/top_level.txt